thoth_doc/__init__.py
thoth_doc/main.py
thoth_doc/parsers.py
thoth_doc/utils.py
thoth_doc-0.0.91.dist-info/METADATA
thoth_doc-0.0.91.dist-info/WHEEL
thoth_doc-0.0.91.dist-info/licenses/LICENSE
thoth_doc-0.0.91.dist-info/RECORD
