Metadata-Version: 2.1
Name: thoth_doc
Version: 0.0.91
Summary: Dependency-free, lightweight docstring parser
Project-URL: Homepage, https://github.com/mariownyou/thoth-doc
Project-URL: Bug Tracker, https://github.com/mariownyou/thoth-doc/issues
Author-email: Lev <smj510black@gmail.com>
License-File: LICENSE
Classifier: License :: OSI Approved :: MIT License
Classifier: Operating System :: OS Independent
Classifier: Programming Language :: Python :: 3
Classifier: Topic :: Documentation
Requires-Python: >=3.7
